[{"RaceId":1,"TrackName":"Turfway Park","SponsorEmail":"pepsi@pepsi.com","SponsorName":"Pepsi","SponsorPhone":"222-444-5555","MaxGroupSize":10,"Members":[{"MemberId":1,"MemberEmail":"tim@williams.com","HorseName":"Darkness","JockeyName":"Tim Williams","Odds":"44-1","HorseColor":"Red","MemberPhone":"456-324-0987"},{"MemberId":2,"MemberEmail":"ar@hope.com","HorseName":"Eureka","JockeyName":"Bob Hope","Odds":"20-1","HorseColor":"White","MemberPhone":"345-0987-2234"},{"MemberId":3,"MemberEmail":"fake@data.com","HorseName":"Energizer Bunny","JockeyName":"Robert Smith","Odds":"9-1","HorseColor":"Blue","MemberPhone":"111-234-0972"}]},{"RaceId":2,"TrackName":"Turfway Park","SponsorEmail":"gh@rq.com","SponsorName":"Nike","SponsorPhone":"845-098-2032","MaxGroupSize":18,"Members":[]},{"RaceId":3,"TrackName":"Del Mar","SponsorEmail":"adidas@deletus.com","SponsorName":"Adidas","SponsorPhone":"764-0987-2345","MaxGroupSize":10,"Members":[{"MemberId":4,"MemberEmail":"horse@horse.com","HorseName":"Merry Go Round","JockeyName":"Tim Albertson","Odds":"20-1","HorseColor":"Yellow","MemberPhone":"222-333-4444"}]},{"RaceId":4,"TrackName":"Oaklawn","SponsorEmail":"jill@wonder.com","SponsorName":"Wonderbread","SponsorPhone":"334-908-1234","MaxGroupSize":15,"Members":[]}]